<!-- X1_Bounty_A1_Wilderness_Kill_Horrus (369399)  -->
<!-- X1_Bounty_A1_Wilderness_Kill_Kankerrot (369404)  -->
<Profile>
<Name>Kill Horrus (369399)</Name>
<KillMonsters>True</KillMonsters>
<PickupLoot>true</PickupLoot>
<GameParams act="OpenWorld" resumeFromSave="False" isPrivate="True" numGames="-1" />
<Order>

  <FunkyWaypoint waypointNumber="6" questId="1"/>
	<WaitTimer questId="1" stepId="2" waitTime="2000" />
	
	<If condition="HasQuest(369404)">		
	
		<!-- Look for him -->
		<SafeMoveTo questId="312429" stepId="2" x="2890" y="2358" z="0" pathPrecision="5" pathPointLimit="250" statusText="" /> 
		<SafeMoveTo questId="312429" stepId="2" x="2676" y="2265" z="0" pathPrecision="5" pathPointLimit="250" statusText="" /> 
		<SafeMoveTo questId="312429" stepId="2" x="2593" y="2140" z="0" pathPrecision="5" pathPointLimit="250" statusText="" /> 
		<SafeMoveTo questId="312429" stepId="2" x="2429" y="2164" z="0" pathPrecision="5" pathPointLimit="250" statusText="" /> 
		<SafeMoveTo questId="312429" stepId="2" x="2328" y="2049" z="0" pathPrecision="5" pathPointLimit="250" statusText="" /> 
		<SafeMoveTo questId="312429" stepId="2" x="2197" y="2039" z="0" pathPrecision="5" pathPointLimit="250" statusText="" /> 
		<HaveBounty questId="369404">		
			<SafeMoveTo questId="312429" stepId="2" x="2371" y="1784" z="0" pathPrecision="5" pathPointLimit="250" statusText="" /> 
		</HaveBounty>			
		<HaveBounty questId="369404">		
			<SafeMoveTo questId="312429" stepId="2" x="2521" y="1721" z="0" pathPrecision="5" pathPointLimit="250" statusText="" /> 
		</HaveBounty>	
		<HaveBounty questId="369404">		
			<SafeMoveTo questId="312429" stepId="2" x="2711" y="1912" z="0" pathPrecision="5" pathPointLimit="250" statusText="" /> 
		</HaveBounty>	
		<HaveBounty questId="369404">		
			<SafeMoveTo questId="312429" stepId="2" x="2897" y="1909" z="0" pathPrecision="5" pathPointLimit="250" statusText="" /> 
		</HaveBounty>	
		<HaveBounty questId="369404">		
			<SafeMoveTo questId="312429" stepId="2" x="3000" y="2102" z="0" pathPrecision="5" pathPointLimit="250" statusText="" /> 
		</HaveBounty>	
		<HaveBounty questId="369404">		
			<SafeMoveTo questId="312429" stepId="2" x="2932" y="2290" z="0" pathPrecision="5" pathPointLimit="250" statusText="" /> 
		</HaveBounty>	
		<HaveBounty questId="369404">		
			<SafeMoveTo questId="312429" stepId="2" x="2799" y="2132" z="0" pathPrecision="5" pathPointLimit="250" statusText="" /> 
		</HaveBounty>	
		<HaveBounty questId="369404">		
			<SafeMoveTo questId="312429" stepId="2" x="2894" y="2035" z="0" pathPrecision="5" pathPointLimit="250" statusText="" /> 
		</HaveBounty>	
		<HaveBounty questId="369404">		
			<SafeMoveTo questId="312429" stepId="2" x="2702" y="2029" z="0" pathPrecision="5" pathPointLimit="250" statusText="" /> 
		</HaveBounty>	
		<HaveBounty questId="369404">		
			<SafeMoveTo questId="312429" stepId="2" x="2489" y="2043" z="0" pathPrecision="5" pathPointLimit="250" statusText="" /> 
		</HaveBounty>	
		<HaveBounty questId="369404">		
			<SafeMoveTo questId="312429" stepId="2" x="2443" y="1901" z="0" pathPrecision="5" pathPointLimit="250" statusText="" /> 
		</HaveBounty>
		<HaveBounty questId="369404">		
			<SafeMoveTo questId="312429" stepId="2" x="2515" y="1866" z="-1" pathPrecision="5" pathPointLimit="250" statusText="" /> 
		</HaveBounty>
		<HaveBounty questId="369404">		
			<SafeMoveTo questId="312429" stepId="2" x="2604" y="1928" z="0" pathPrecision="5" pathPointLimit="250" statusText="" /> 
		</HaveBounty>
		<HaveBounty questId="369404">	
			<TrinityExploreDungeon questId="1" stepId="2" until="FullyExplored" boxTolerance=".10" boxSize="9" stayAfterBounty="False"/>
		</HaveBounty>	
	
	</If>
	
	<If condition="HasQuest(369399)">	
	
		<!-- Look for him -->
		<SafeMoveTo questId="312429" stepId="2" x="2890" y="2358" z="0" pathPrecision="5" pathPointLimit="250" statusText="" /> 
		<SafeMoveTo questId="312429" stepId="2" x="2676" y="2265" z="0" pathPrecision="5" pathPointLimit="250" statusText="" /> 
		<SafeMoveTo questId="312429" stepId="2" x="2593" y="2140" z="0" pathPrecision="5" pathPointLimit="250" statusText="" /> 
		<SafeMoveTo questId="312429" stepId="2" x="2429" y="2164" z="0" pathPrecision="5" pathPointLimit="250" statusText="" /> 
		<SafeMoveTo questId="312429" stepId="2" x="2328" y="2049" z="0" pathPrecision="5" pathPointLimit="250" statusText="" /> 
		<SafeMoveTo questId="312429" stepId="2" x="2197" y="2039" z="0" pathPrecision="5" pathPointLimit="250" statusText="" /> 
		<HaveBounty questId="369399">		
			<SafeMoveTo questId="312429" stepId="2" x="2371" y="1784" z="0" pathPrecision="5" pathPointLimit="250" statusText="" /> 
		</HaveBounty>			
		<HaveBounty questId="369399">		
			<SafeMoveTo questId="312429" stepId="2" x="2521" y="1721" z="0" pathPrecision="5" pathPointLimit="250" statusText="" /> 
		</HaveBounty>	
		<HaveBounty questId="369399">		
			<SafeMoveTo questId="312429" stepId="2" x="2711" y="1912" z="0" pathPrecision="5" pathPointLimit="250" statusText="" /> 
		</HaveBounty>	
		<HaveBounty questId="369399">		
			<SafeMoveTo questId="312429" stepId="2" x="2897" y="1909" z="0" pathPrecision="5" pathPointLimit="250" statusText="" /> 
		</HaveBounty>	
		<HaveBounty questId="369399">		
			<SafeMoveTo questId="312429" stepId="2" x="3000" y="2102" z="0" pathPrecision="5" pathPointLimit="250" statusText="" /> 
		</HaveBounty>	
		<HaveBounty questId="369399">		
			<SafeMoveTo questId="312429" stepId="2" x="2932" y="2290" z="0" pathPrecision="5" pathPointLimit="250" statusText="" /> 
		</HaveBounty>	
		<HaveBounty questId="369399">		
			<SafeMoveTo questId="312429" stepId="2" x="2799" y="2132" z="0" pathPrecision="5" pathPointLimit="250" statusText="" /> 
		</HaveBounty>	
		<HaveBounty questId="369399">		
			<SafeMoveTo questId="312429" stepId="2" x="2894" y="2035" z="0" pathPrecision="5" pathPointLimit="250" statusText="" /> 
		</HaveBounty>	
		<HaveBounty questId="369399">		
			<SafeMoveTo questId="312429" stepId="2" x="2702" y="2029" z="0" pathPrecision="5" pathPointLimit="250" statusText="" /> 
		</HaveBounty>	
		<HaveBounty questId="369399">		
			<SafeMoveTo questId="312429" stepId="2" x="2489" y="2043" z="0" pathPrecision="5" pathPointLimit="250" statusText="" /> 
		</HaveBounty>	
		<HaveBounty questId="369399">		
			<SafeMoveTo questId="312429" stepId="2" x="2443" y="1901" z="0" pathPrecision="5" pathPointLimit="250" statusText="" /> 
		</HaveBounty>
		<HaveBounty questId="369399">		
			<SafeMoveTo questId="312429" stepId="2" x="2515" y="1866" z="-1" pathPrecision="5" pathPointLimit="250" statusText="" /> 
		</HaveBounty>
		<HaveBounty questId="369399">		
			<SafeMoveTo questId="312429" stepId="2" x="2604" y="1928" z="0" pathPrecision="5" pathPointLimit="250" statusText="" /> 
		</HaveBounty>
		<HaveBounty questId="369399">	
			<TrinityExploreDungeon questId="1" stepId="2" until="FullyExplored" boxTolerance=".10" boxSize="9" stayAfterBounty="False"/>
		</HaveBounty>	
	
	</If>
	
	 <LoadProfile profile="_Act1BountyLoader.xml" />
	
</Order>
</Profile>